{
    "seniority": "3 года",
    "workplaces": [

        {
            "organisation": "ООО Рога и Копыта",
            "position" : "Разработчик",
            "start" : "01.01.21",
            "end" : "01.01.23",
            "projects" : [
                {
                    "description" : "Сделал такой-то проект",
                    "stack" : "Python | Postgres | Redis | FastAPI",
                    "comment" : "интересные кейсы"
                },
                {
                    "description" : "Сделал такой-то проект",
                    "stack" : "Python | Postgres | Redis | FastAPI",
                    "comment" : "интересные кейсы"
                }
            ]
        },
        {
            "organisation": "ООО Копыта и Рога",
            "position" : "Разработчик",
            "start" : "01.01.20",
            "end" : "01.01.21",
            "projects" : [
                {
                    "description" : "Сделал такой-то проект",
                    "stack" : "Java | MariaDB | MongoDB | Spring",
                    "comment" : "интересные кейсы"
                },
                {
                    "description" : "Сделал такой-то проект",
                    "stack" : "Java | MariaDB | MongoDB | Spring",
                    "comment" : "интересные кейсы"
                }
            ]
        }
    ]
}